chart_image_clients/__init__.py
chart_image_clients/plotly_client.py
chart_image_clients-1.1.3.dist-info/LICENSE.txt
chart_image_clients-1.1.3.dist-info/METADATA
chart_image_clients-1.1.3.dist-info/WHEEL
chart_image_clients-1.1.3.dist-info/top_level.txt
chart_image_clients-1.1.3.dist-info/RECORD
